haystack_integrations/components/retrievers/py.typed
haystack_integrations/components/retrievers/mongodb_atlas/__init__.py
haystack_integrations/components/retrievers/mongodb_atlas/embedding_retriever.py
haystack_integrations/components/retrievers/mongodb_atlas/full_text_retriever.py
haystack_integrations/document_stores/py.typed
haystack_integrations/document_stores/mongodb_atlas/__init__.py
haystack_integrations/document_stores/mongodb_atlas/document_store.py
haystack_integrations/document_stores/mongodb_atlas/filters.py
mongodb_atlas_haystack-3.5.0.dist-info/METADATA
mongodb_atlas_haystack-3.5.0.dist-info/WHEEL
mongodb_atlas_haystack-3.5.0.dist-info/licenses/LICENSE.txt
mongodb_atlas_haystack-3.5.0.dist-info/RECORD
